[
  {
    "email": "biqiang.xiao@adp.com",
    "name": "Biqiang",
    "ref": ""
  },
  {
    "email": "james.gu@adp.com",
    "name": "James Gu",
    "ref": "https://rally1.rallydev.com/slm/webservice/v2.0/user/12332327104"
  },
  {
    "email": "richard.sefton@adp.com",
    "name": "Richard Sefton",
    "ref": "https://rally1.rallydev.com/slm/webservice/v2.0/user/15325042274"
  },
  {
    "email": "ke.xu2@adp.com",
    "name": "Ke XU",
    "ref": "https://rally1.rallydev.com/slm/webservice/v2.0/user/36675776793"
  },
  {
    "email": "rooby.chen@adp.com",
    "name": "Rooby Chen",
    "ref": "https://rally1.rallydev.com/slm/webservice/v2.0/user/12332286377"
  },
  {
    "email": "madhuraj.soudathikar@adp.com",
    "name": "MadhuRaj Soudathikar",
    "ref": "https://rally1.rallydev.com/slm/webservice/v2.0/user/60781793883"
  },
  {
    "email": "raghupathi.jella@adp.com",
    "name": "Raghupathi Jella",
    "ref": "https://rally1.rallydev.com/slm/webservice/v2.0/user/55612858068"
  },
  {
    "email": "edmond.guan@adp.com",
    "name": "Edmond Guan",
    "ref": "https://rally1.rallydev.com/slm/webservice/v2.0/user/165064525256"
  },
  {
    "email": "nolan.zhang@adp.com",
    "name": "Nolan Zhang",
    "ref": "https://rally1.rallydev.com/slm/webservice/v2.0/user/172345771032"
  },
  {
    "email": "kadari.praneeth@adp.com",
    "name": "Praneeth",
    "ref": ""
  },
  {
    "email": "pedro.bravo@adp.com",
    "name": "Pedro Bravo",
    "ref": "https://rally1.rallydev.com/slm/webservice/v2.0/user/12332332573"
  },
  {
    "email": "richard.ribier@adp.com",
    "name": "Richard Ribier",
    "ref": "https://rally1.rallydev.com/slm/webservice/v2.0/user/12332105132"
  },
  {
    "email": "francois.compain@adp.com",
    "name": "Francois Compain",
    "ref": "https://rally1.rallydev.com/slm/webservice/v2.0/user/14644714632"
  },
  {
    "email": "sandy.hu@adp.com",
    "name": "Sandy Hu",
    "ref": "https://rally1.rallydev.com/slm/webservice/v2.0/user/15569498469"
  },
  {
    "email": "raghavendra.reddy.bokka@adp.com",
    "name": "Raghavendra Reddy B",
    "ref": "https://rally1.rallydev.com/slm/webservice/v2.0/user/114430286448"
  },
  {
    "email": "vincent.wen@adpl.com",
    "name": "Vincent",
    "ref": ""
  },
  {
    "email": "wenqian.chen@adp.com",
    "name": "Wenqian Chen",
    "ref": "https://rally1.rallydev.com/slm/webservice/v2.0/user/21723583984"
  },
  {
    "email": "amarnath.gangigunta@adp.com",
    "name": "Amar G",
    "ref": ""
  }
]